{
  "text": "(Evanildo Bechara UERJ/ UFF )",
  "denotations": [
    {
      "id": "T1",
      "obj": "individuo",
      "span": {
        "begin": 1,
        "end": 17
      }
    },
    {
      "id": "T2",
      "obj": "organizacao",
      "span": {
        "begin": 18,
        "end": 22
      }
    },
    {
      "id": "T3",
      "obj": "organizacao",
      "span": {
        "begin": 24,
        "end": 27
      }
    }
  ],
  "relations": [
    {
      "id": "R1",
      "pred": "vinculo_inst",
      "subj": "T2",
      "obj": "T1"
    },
    {
      "id": "R2",
      "pred": "vinculo_inst",
      "subj": "T3",
      "obj": "T1"
    }
  ]
}