{
  "text": "Na passada sexta-feira , o Banco Central Europeu ( BCE ) fixou a taxa de câmbio oficial a 1,4692 dólares , um valor que corresponde a mais 17% face ao câmbio média calculado para 2006 , quando a moeda única europeia se fixou em 1,2556 dólares , segundo dados do BCE para a média anual.",
  "denotations": [
    {
      "id": "T1",
      "obj": "tempo",
      "span": {
        "begin": 0,
        "end": 22
      }
    },
    {
      "id": "T2",
      "obj": "organizacao",
      "span": {
        "begin": 27,
        "end": 48
      }
    },
    {
      "id": "T3",
      "obj": "organizacao",
      "span": {
        "begin": 51,
        "end": 54
      }
    },
    {
      "id": "T4",
      "obj": "valor",
      "span": {
        "begin": 90,
        "end": 104
      }
    },
    {
      "id": "T5",
      "obj": "valor",
      "span": {
        "begin": 134,
        "end": 142
      }
    },
    {
      "id": "T6",
      "obj": "tempo",
      "span": {
        "begin": 174,
        "end": 183
      }
    },
    {
      "id": "T7",
      "obj": "valor",
      "span": {
        "begin": 228,
        "end": 242
      }
    },
    {
      "id": "T8",
      "obj": "organizacao",
      "span": {
        "begin": 262,
        "end": 265
      }
    }
  ],
  "relations": [
    {
      "id": "R1",
      "pred": "ident",
      "subj": "T3",
      "obj": "T2"
    },
    {
      "id": "R2",
      "pred": "ident",
      "subj": "T8",
      "obj": "T2"
    }
  ]
}