{
  "text": "Desde quando é que a Suíça é membro da UNESCO? Quem era a presidente do comité suíço da UNESCO em 1995? Quantos estados-membros tinha a organização em 1995? O prémio UNESCO da Paz é de quantos dólares?",
  "denotations": [
    {
      "id": "T1",
      "obj": "local",
      "span": {
        "begin": 21,
        "end": 26
      }
    },
    {
      "id": "T2",
      "obj": "organizacao",
      "span": {
        "begin": 39,
        "end": 45
      }
    },
    {
      "id": "T3",
      "obj": "organizacao",
      "span": {
        "begin": 88,
        "end": 94
      }
    },
    {
      "id": "T4",
      "obj": "tempo",
      "span": {
        "begin": 95,
        "end": 102
      }
    },
    {
      "id": "T5",
      "obj": "tempo",
      "span": {
        "begin": 148,
        "end": 155
      }
    },
    {
      "id": "T6",
      "obj": "outro",
      "span": {
        "begin": 166,
        "end": 172
      }
    },
    {
      "id": "T7",
      "obj": "abstraccao",
      "span": {
        "begin": 176,
        "end": 179
      }
    }
  ],
  "relations": [
    {
      "id": "R1",
      "pred": "inclui",
      "subj": "T2",
      "obj": "T1"
    },
    {
      "id": "R2",
      "pred": "ident",
      "subj": "T3",
      "obj": "T2"
    },
    {
      "id": "R3",
      "pred": "ident",
      "subj": "T5",
      "obj": "T4"
    },
    {
      "id": "R4",
      "pred": "outrarel",
      "subj": "T6",
      "obj": "T2"
    }
  ]
}